odoo/addons/project_tag_hierarchy/README.rst
odoo/addons/project_tag_hierarchy/__init__.py
odoo/addons/project_tag_hierarchy/__manifest__.py
odoo/addons/project_tag_hierarchy/i18n/es.po
odoo/addons/project_tag_hierarchy/i18n/it.po
odoo/addons/project_tag_hierarchy/i18n/project_tag_hierarchy.pot
odoo/addons/project_tag_hierarchy/i18n/pt_BR.po
odoo/addons/project_tag_hierarchy/i18n/sv.po
odoo/addons/project_tag_hierarchy/models/__init__.py
odoo/addons/project_tag_hierarchy/models/project_tags.py
odoo/addons/project_tag_hierarchy/readme/CONTRIBUTORS.md
odoo/addons/project_tag_hierarchy/readme/DESCRIPTION.md
odoo/addons/project_tag_hierarchy/static/description/icon.png
odoo/addons/project_tag_hierarchy/static/description/index.html
odoo/addons/project_tag_hierarchy/tests/__init__.py
odoo/addons/project_tag_hierarchy/tests/test_project_tag_hierarchy.py
odoo/addons/project_tag_hierarchy/views/project_tags_views.xml
odoo_addon_project_tag_hierarchy-18.0.1.0.1.dist-info/METADATA
odoo_addon_project_tag_hierarchy-18.0.1.0.1.dist-info/WHEEL
odoo_addon_project_tag_hierarchy-18.0.1.0.1.dist-info/top_level.txt
odoo_addon_project_tag_hierarchy-18.0.1.0.1.dist-info/RECORD
